tarhash.py
tarhash-0.1.0.dist-info/METADATA
tarhash-0.1.0.dist-info/WHEEL
tarhash-0.1.0.dist-info/entry_points.txt
tarhash-0.1.0.dist-info/licenses/LICENSE-APACHE.txt
tarhash-0.1.0.dist-info/licenses/LICENSE-MIT.txt
tarhash-0.1.0.dist-info/RECORD
