Metadata-Version: 2.4
Name: tarhash
Version: 0.1.0
Summary: Hashes the entries in a tarfile without extracting them
Project-URL: Source, https://github.com/Techcable/tarhash
Author: Techcable
License-Expression: MIT OR Apache-2.0
License-File: LICENSE-APACHE.txt
License-File: LICENSE-MIT.txt
Keywords: checksum,hash,tar
Classifier: Development Status :: 4 - Beta
Classifier: Environment :: Console
Classifier: Programming Language :: Python :: 3
Classifier: Topic :: Security :: Cryptography
Classifier: Topic :: System :: Archiving
Classifier: Topic :: System :: Archiving :: Compression
Classifier: Topic :: Utilities
Requires-Python: >=3.9
Requires-Dist: click~=8.0
Provides-Extra: all
Requires-Dist: backports-zstd; (python_version < '3.14') and extra == 'all'
Requires-Dist: blake3; extra == 'all'
Requires-Dist: xxhash; extra == 'all'
Provides-Extra: blake3
Requires-Dist: blake3; extra == 'blake3'
Provides-Extra: recommended
Requires-Dist: backports-zstd; (python_version < '3.14') and extra == 'recommended'
Requires-Dist: blake3; extra == 'recommended'
Requires-Dist: xxhash; extra == 'recommended'
Provides-Extra: xxhash
Requires-Dist: xxhash; extra == 'xxhash'
Provides-Extra: zstd
Requires-Dist: backports-zstd; (python_version < '3.14') and extra == 'zstd'
